{"connector_id":"grid/intensity/mock","connector_version":"0.1.0","payload":{"metadata":{"algorithm":"seasonal_sinusoid","connector":"grid/intensity/mock","data_points":58,"region_offset":190,"seed":"3882df16c0467ec7ddcdc57607aa9718636fb7c417e4a609149c98cbbb6d3fd6","version":"0.1.0"},"region":"EU-DE","resolution":"hour","series":[{"quality":"simulated","ts":"2025-11-22T21:00:00Z","unit":"gCO2/kWh","value":"348.6"},{"quality":"simulated","ts":"2025-11-22T22:00:00Z","unit":"gCO2/kWh","value":"390"},{"quality":"simulated","ts":"2025-11-22T23:00:00Z","unit":"gCO2/kWh","value":"438.2"},{"quality":"simulated","ts":"2025-11-23T00:00:00Z","unit":"gCO2/kWh","value":"490"},{"quality":"simulated","ts":"2025-11-23T01:00:00Z","unit":"gCO2/kWh","value":"541.8"},{"quality":"simulated","ts":"2025-11-23T02:00:00Z","unit":"gCO2/kWh","value":"590"},{"quality":"simulated","ts":"2025-11-23T03:00:00Z","unit":"gCO2/kWh","value":"631.4"},{"quality":"simulated","ts":"2025-11-23T04:00:00Z","unit":"gCO2/kWh","value":"663.2"},{"quality":"simulated","ts":"2025-11-23T05:00:00Z","unit":"gCO2/kWh","value":"683.2"},{"quality":"simulated","ts":"2025-11-23T06:00:00Z","unit":"gCO2/kWh","value":"690"},{"quality":"simulated","ts":"2025-11-23T07:00:00Z","unit":"gCO2/kWh","value":"683.2"},{"quality":"simulated","ts":"2025-11-23T08:00:00Z","unit":"gCO2/kWh","value":"663.2"},{"quality":"simulated","ts":"2025-11-23T09:00:00Z","unit":"gCO2/kWh","value":"631.4"},{"quality":"simulated","ts":"2025-11-23T10:00:00Z","unit":"gCO2/kWh","value":"590"},{"quality":"simulated","ts":"2025-11-23T11:00:00Z","unit":"gCO2/kWh","value":"541.8"},{"quality":"simulated","ts":"2025-11-23T12:00:00Z","unit":"gCO2/kWh","value":"490"},{"quality":"simulated","ts":"2025-11-23T13:00:00Z","unit":"gCO2/kWh","value":"438.2"},{"quality":"simulated","ts":"2025-11-23T14:00:00Z","unit":"gCO2/kWh","value":"390"},{"quality":"simulated","ts":"2025-11-23T15:00:00Z","unit":"gCO2/kWh","value":"348.6"},{"quality":"simulated","ts":"2025-11-23T16:00:00Z","unit":"gCO2/kWh","value":"316.8"},{"quality":"simulated","ts":"2025-11-23T17:00:00Z","unit":"gCO2/kWh","value":"296.8"},{"quality":"simulated","ts":"2025-11-23T18:00:00Z","unit":"gCO2/kWh","value":"290"},{"quality":"simulated","ts":"2025-11-23T19:00:00Z","unit":"gCO2/kWh","value":"296.8"},{"quality":"simulated","ts":"2025-11-23T20:00:00Z","unit":"gCO2/kWh","value":"316.8"},{"quality":"simulated","ts":"2025-11-23T21:00:00Z","unit":"gCO2/kWh","value":"348.6"},{"quality":"simulated","ts":"2025-11-23T22:00:00Z","unit":"gCO2/kWh","value":"390"},{"quality":"simulated","ts":"2025-11-23T23:00:00Z","unit":"gCO2/kWh","value":"438.2"},{"quality":"simulated","ts":"2025-11-24T00:00:00Z","unit":"gCO2/kWh","value":"490"},{"quality":"simulated","ts":"2025-11-24T01:00:00Z","unit":"gCO2/kWh","value":"541.8"},{"quality":"simulated","ts":"2025-11-24T02:00:00Z","unit":"gCO2/kWh","value":"590"},{"quality":"simulated","ts":"2025-11-24T03:00:00Z","unit":"gCO2/kWh","value":"631.4"},{"quality":"simulated","ts":"2025-11-24T04:00:00Z","unit":"gCO2/kWh","value":"663.2"},{"quality":"simulated","ts":"2025-11-24T05:00:00Z","unit":"gCO2/kWh","value":"683.2"},{"quality":"simulated","ts":"2025-11-24T06:00:00Z","unit":"gCO2/kWh","value":"690"},{"quality":"simulated","ts":"2025-11-24T07:00:00Z","unit":"gCO2/kWh","value":"683.2"},{"quality":"simulated","ts":"2025-11-24T08:00:00Z","unit":"gCO2/kWh","value":"663.2"},{"quality":"simulated","ts":"2025-11-24T09:00:00Z","unit":"gCO2/kWh","value":"631.4"},{"quality":"simulated","ts":"2025-11-24T10:00:00Z","unit":"gCO2/kWh","value":"590"},{"quality":"simulated","ts":"2025-11-24T11:00:00Z","unit":"gCO2/kWh","value":"541.8"},{"quality":"simulated","ts":"2025-11-24T12:00:00Z","unit":"gCO2/kWh","value":"490"},{"quality":"simulated","ts":"2025-11-24T13:00:00Z","unit":"gCO2/kWh","value":"438.2"},{"quality":"simulated","ts":"2025-11-24T14:00:00Z","unit":"gCO2/kWh","value":"390"},{"quality":"simulated","ts":"2025-11-24T15:00:00Z","unit":"gCO2/kWh","value":"348.6"},{"quality":"simulated","ts":"2025-11-24T16:00:00Z","unit":"gCO2/kWh","value":"316.8"},{"quality":"simulated","ts":"2025-11-24T17:00:00Z","unit":"gCO2/kWh","value":"296.8"},{"quality":"simulated","ts":"2025-11-24T18:00:00Z","unit":"gCO2/kWh","value":"290"},{"quality":"simulated","ts":"2025-11-24T19:00:00Z","unit":"gCO2/kWh","value":"296.8"},{"quality":"simulated","ts":"2025-11-24T20:00:00Z","unit":"gCO2/kWh","value":"316.8"},{"quality":"simulated","ts":"2025-11-24T21:00:00Z","unit":"gCO2/kWh","value":"348.6"},{"quality":"simulated","ts":"2025-11-24T22:00:00Z","unit":"gCO2/kWh","value":"390"},{"quality":"simulated","ts":"2025-11-24T23:00:00Z","unit":"gCO2/kWh","value":"438.2"},{"quality":"simulated","ts":"2025-11-25T00:00:00Z","unit":"gCO2/kWh","value":"490"},{"quality":"simulated","ts":"2025-11-25T01:00:00Z","unit":"gCO2/kWh","value":"541.8"},{"quality":"simulated","ts":"2025-11-25T02:00:00Z","unit":"gCO2/kWh","value":"590"},{"quality":"simulated","ts":"2025-11-25T03:00:00Z","unit":"gCO2/kWh","value":"631.4"},{"quality":"simulated","ts":"2025-11-25T04:00:00Z","unit":"gCO2/kWh","value":"663.2"},{"quality":"simulated","ts":"2025-11-25T05:00:00Z","unit":"gCO2/kWh","value":"683.2"},{"quality":"simulated","ts":"2025-11-25T06:00:00Z","unit":"gCO2/kWh","value":"690"}],"unit":"gCO2/kWh"},"provenance":{"connector_id":"grid/intensity/mock","connector_version":"0.1.0","metadata":{"data_points":58,"end":"2025-11-25T07:00:00+00:00","region":"EU-DE","resolution":"hour","start":"2025-11-22T21:00:00+00:00"},"mode":"record","query_hash":"4b15ce9af947d4e977ac6dc87b1e0fda855cc77363b8b86f1c409d2c0b4e7869","schema_hash":"2cf663a8a03d50acb0c1df2fba40940ffb4f63f0d1882a6386a70320e2bc06f6","seed":"3882df16c0467ec7ddcdc57607aa9718636fb7c417e4a609149c98cbbb6d3fd6","snapshot_id":"72534163ac63a13a33d067c73ddc1e8ca958cd6fc16b7ab86ae955844da32c5a","timestamp":"2025-10-09T05:19:09.961065Z"},"schema":{"payload_model":"GridIntensityPayload","provenance_model":"ConnectorProvenance"}}